{
	"iconDefinitions": {
		"_root_folder": {
			"iconPath": "./images/root_folder_closed.png"
		},
		"_root_folder_open": {
			"iconPath": "./images/root_folder_open.png"
		},
		"_folder": {
			"iconPath": "./images/folder_closed.png"
		},
		"_folder_open": {
			"iconPath": "./images/folder_open.png"
		},
		"_file": {
			"iconPath": "./images/file.png"
		},
		"_f_json": {
		  "iconPath": "./images/json.png"
		}
	},

	"folderExpanded": "_folder_open",
	"folder": "_folder",
	"file": "_file",
	"rootFolderExpanded": "_root_folder_open",
	"rootFolder": "_root_folder",
	"fileExtensions": {
		"json": "_f_json",
		"json-tmlanguage": "_f_json"
	},
	"fileNames": {
		// icons by file name
	},
	"languageIds": {
		// icons by language id
	},
	"highContrast": {
		// overrides for high contrast
	}
}